{
  "translation": "BSB",
  "license": "Public Domain",
  "source": "https://bible.helloao.org",
  "canonGroup": "protocanon",
  "bookCount": 66,
  "books": [
    {
      "id": "GEN",
      "name": "Genesis",
      "order": 1,
      "testament": "OT",
      "canonGroup": "protocanon",
      "numberOfChapters": 50,
      "totalNumberOfVerses": 1533
    },
    {
      "id": "EXO",
      "name": "Exodus",
      "order": 2,
      "testament": "OT",
      "canonGroup": "protocanon",
      "numberOfChapters": 40,
      "totalNumberOfVerses": 1213
    },
    {
      "id": "LEV",
      "name": "Leviticus",
      "order": 3,
      "testament": "OT",
      "canonGroup": "protocanon",
      "numberOfChapters": 27,
      "totalNumberOfVerses": 859
    },
    {
      "id": "NUM",
      "name": "Numbers",
      "order": 4,
      "testament": "OT",
      "canonGroup": "protocanon",
      "numberOfChapters": 36,
      "totalNumberOfVerses": 1288
    },
    {
      "id": "DEU",
      "name": "Deuteronomy",
      "order": 5,
      "testament": "OT",
      "canonGroup": "protocanon",
      "numberOfChapters": 34,
      "totalNumberOfVerses": 959
    },
    {
      "id": "JOS",
      "name": "Joshua",
      "order": 6,
      "testament": "OT",
      "canonGroup": "protocanon",
      "numberOfChapters": 24,
      "totalNumberOfVerses": 658
    },
    {
      "id": "JDG",
      "name": "Judges",
      "order": 7,
      "testament": "OT",
      "canonGroup": "protocanon",
      "numberOfChapters": 21,
      "totalNumberOfVerses": 618
    },
    {
      "id": "RUT",
      "name": "Ruth",
      "order": 8,
      "testament": "OT",
      "canonGroup": "protocanon",
      "numberOfChapters": 4,
      "totalNumberOfVerses": 85
    },
    {
      "id": "1SA",
      "name": "1 Samuel",
      "order": 9,
      "testament": "OT",
      "canonGroup": "protocanon",
      "numberOfChapters": 31,
      "totalNumberOfVerses": 810
    },
    {
      "id": "2SA",
      "name": "2 Samuel",
      "order": 10,
      "testament": "OT",
      "canonGroup": "protocanon",
      "numberOfChapters": 24,
      "totalNumberOfVerses": 695
    },
    {
      "id": "1KI",
      "name": "1 Kings",
      "order": 11,
      "testament": "OT",
      "canonGroup": "protocanon",
      "numberOfChapters": 22,
      "totalNumberOfVerses": 816
    },
    {
      "id": "2KI",
      "name": "2 Kings",
      "order": 12,
      "testament": "OT",
      "canonGroup": "protocanon",
      "numberOfChapters": 25,
      "totalNumberOfVerses": 719
    },
    {
      "id": "1CH",
      "name": "1 Chronicles",
      "order": 13,
      "testament": "OT",
      "canonGroup": "protocanon",
      "numberOfChapters": 29,
      "totalNumberOfVerses": 942
    },
    {
      "id": "2CH",
      "name": "2 Chronicles",
      "order": 14,
      "testament": "OT",
      "canonGroup": "protocanon",
      "numberOfChapters": 36,
      "totalNumberOfVerses": 822
    },
    {
      "id": "EZR",
      "name": "Ezra",
      "order": 15,
      "testament": "OT",
      "canonGroup": "protocanon",
      "numberOfChapters": 10,
      "totalNumberOfVerses": 280
    },
    {
      "id": "NEH",
      "name": "Nehemiah",
      "order": 16,
      "testament": "OT",
      "canonGroup": "protocanon",
      "numberOfChapters": 13,
      "totalNumberOfVerses": 406
    },
    {
      "id": "EST",
      "name": "Esther",
      "order": 17,
      "testament": "OT",
      "canonGroup": "protocanon",
      "numberOfChapters": 10,
      "totalNumberOfVerses": 167
    },
    {
      "id": "JOB",
      "name": "Job",
      "order": 18,
      "testament": "OT",
      "canonGroup": "protocanon",
      "numberOfChapters": 42,
      "totalNumberOfVerses": 1070
    },
    {
      "id": "PSA",
      "name": "Psalms",
      "order": 19,
      "testament": "OT",
      "canonGroup": "protocanon",
      "numberOfChapters": 150,
      "totalNumberOfVerses": 2461
    },
    {
      "id": "PRO",
      "name": "Proverbs",
      "order": 20,
      "testament": "OT",
      "canonGroup": "protocanon",
      "numberOfChapters": 31,
      "totalNumberOfVerses": 915
    },
    {
      "id": "ECC",
      "name": "Ecclesiastes",
      "order": 21,
      "testament": "OT",
      "canonGroup": "protocanon",
      "numberOfChapters": 12,
      "totalNumberOfVerses": 222
    },
    {
      "id": "SNG",
      "name": "Song of Solomon",
      "order": 22,
      "testament": "OT",
      "canonGroup": "protocanon",
      "numberOfChapters": 8,
      "totalNumberOfVerses": 117
    },
    {
      "id": "ISA",
      "name": "Isaiah",
      "order": 23,
      "testament": "OT",
      "canonGroup": "protocanon",
      "numberOfChapters": 66,
      "totalNumberOfVerses": 1292
    },
    {
      "id": "JER",
      "name": "Jeremiah",
      "order": 24,
      "testament": "OT",
      "canonGroup": "protocanon",
      "numberOfChapters": 52,
      "totalNumberOfVerses": 1364
    },
    {
      "id": "LAM",
      "name": "Lamentations",
      "order": 25,
      "testament": "OT",
      "canonGroup": "protocanon",
      "numberOfChapters": 5,
      "totalNumberOfVerses": 154
    },
    {
      "id": "EZK",
      "name": "Ezekiel",
      "order": 26,
      "testament": "OT",
      "canonGroup": "protocanon",
      "numberOfChapters": 48,
      "totalNumberOfVerses": 1273
    },
    {
      "id": "DAN",
      "name": "Daniel",
      "order": 27,
      "testament": "OT",
      "canonGroup": "protocanon",
      "numberOfChapters": 12,
      "totalNumberOfVerses": 357
    },
    {
      "id": "HOS",
      "name": "Hosea",
      "order": 28,
      "testament": "OT",
      "canonGroup": "protocanon",
      "numberOfChapters": 14,
      "totalNumberOfVerses": 197
    },
    {
      "id": "JOL",
      "name": "Joel",
      "order": 29,
      "testament": "OT",
      "canonGroup": "protocanon",
      "numberOfChapters": 3,
      "totalNumberOfVerses": 73
    },
    {
      "id": "AMO",
      "name": "Amos",
      "order": 30,
      "testament": "OT",
      "canonGroup": "protocanon",
      "numberOfChapters": 9,
      "totalNumberOfVerses": 146
    },
    {
      "id": "OBA",
      "name": "Obadiah",
      "order": 31,
      "testament": "OT",
      "canonGroup": "protocanon",
      "numberOfChapters": 1,
      "totalNumberOfVerses": 21
    },
    {
      "id": "JON",
      "name": "Jonah",
      "order": 32,
      "testament": "OT",
      "canonGroup": "protocanon",
      "numberOfChapters": 4,
      "totalNumberOfVerses": 48
    },
    {
      "id": "MIC",
      "name": "Micah",
      "order": 33,
      "testament": "OT",
      "canonGroup": "protocanon",
      "numberOfChapters": 7,
      "totalNumberOfVerses": 105
    },
    {
      "id": "NAM",
      "name": "Nahum",
      "order": 34,
      "testament": "OT",
      "canonGroup": "protocanon",
      "numberOfChapters": 3,
      "totalNumberOfVerses": 47
    },
    {
      "id": "HAB",
      "name": "Habakkuk",
      "order": 35,
      "testament": "OT",
      "canonGroup": "protocanon",
      "numberOfChapters": 3,
      "totalNumberOfVerses": 56
    },
    {
      "id": "ZEP",
      "name": "Zephaniah",
      "order": 36,
      "testament": "OT",
      "canonGroup": "protocanon",
      "numberOfChapters": 3,
      "totalNumberOfVerses": 53
    },
    {
      "id": "HAG",
      "name": "Haggai",
      "order": 37,
      "testament": "OT",
      "canonGroup": "protocanon",
      "numberOfChapters": 2,
      "totalNumberOfVerses": 38
    },
    {
      "id": "ZEC",
      "name": "Zechariah",
      "order": 38,
      "testament": "OT",
      "canonGroup": "protocanon",
      "numberOfChapters": 14,
      "totalNumberOfVerses": 211
    },
    {
      "id": "MAL",
      "name": "Malachi",
      "order": 39,
      "testament": "OT",
      "canonGroup": "protocanon",
      "numberOfChapters": 4,
      "totalNumberOfVerses": 55
    },
    {
      "id": "MAT",
      "name": "Matthew",
      "order": 40,
      "testament": "NT",
      "canonGroup": "protocanon",
      "numberOfChapters": 28,
      "totalNumberOfVerses": 1068
    },
    {
      "id": "MRK",
      "name": "Mark",
      "order": 41,
      "testament": "NT",
      "canonGroup": "protocanon",
      "numberOfChapters": 16,
      "totalNumberOfVerses": 673
    },
    {
      "id": "LUK",
      "name": "Luke",
      "order": 42,
      "testament": "NT",
      "canonGroup": "protocanon",
      "numberOfChapters": 24,
      "totalNumberOfVerses": 1149
    },
    {
      "id": "JHN",
      "name": "John",
      "order": 43,
      "testament": "NT",
      "canonGroup": "protocanon",
      "numberOfChapters": 21,
      "totalNumberOfVerses": 878
    },
    {
      "id": "ACT",
      "name": "Acts",
      "order": 44,
      "testament": "NT",
      "canonGroup": "protocanon",
      "numberOfChapters": 28,
      "totalNumberOfVerses": 1003
    },
    {
      "id": "ROM",
      "name": "Romans",
      "order": 45,
      "testament": "NT",
      "canonGroup": "protocanon",
      "numberOfChapters": 16,
      "totalNumberOfVerses": 432
    },
    {
      "id": "1CO",
      "name": "1 Corinthians",
      "order": 46,
      "testament": "NT",
      "canonGroup": "protocanon",
      "numberOfChapters": 16,
      "totalNumberOfVerses": 437
    },
    {
      "id": "2CO",
      "name": "2 Corinthians",
      "order": 47,
      "testament": "NT",
      "canonGroup": "protocanon",
      "numberOfChapters": 13,
      "totalNumberOfVerses": 257
    },
    {
      "id": "GAL",
      "name": "Galatians",
      "order": 48,
      "testament": "NT",
      "canonGroup": "protocanon",
      "numberOfChapters": 6,
      "totalNumberOfVerses": 149
    },
    {
      "id": "EPH",
      "name": "Ephesians",
      "order": 49,
      "testament": "NT",
      "canonGroup": "protocanon",
      "numberOfChapters": 6,
      "totalNumberOfVerses": 155
    },
    {
      "id": "PHP",
      "name": "Philippians",
      "order": 50,
      "testament": "NT",
      "canonGroup": "protocanon",
      "numberOfChapters": 4,
      "totalNumberOfVerses": 104
    },
    {
      "id": "COL",
      "name": "Colossians",
      "order": 51,
      "testament": "NT",
      "canonGroup": "protocanon",
      "numberOfChapters": 4,
      "totalNumberOfVerses": 95
    },
    {
      "id": "1TH",
      "name": "1 Thessalonians",
      "order": 52,
      "testament": "NT",
      "canonGroup": "protocanon",
      "numberOfChapters": 5,
      "totalNumberOfVerses": 89
    },
    {
      "id": "2TH",
      "name": "2 Thessalonians",
      "order": 53,
      "testament": "NT",
      "canonGroup": "protocanon",
      "numberOfChapters": 3,
      "totalNumberOfVerses": 47
    },
    {
      "id": "1TI",
      "name": "1 Timothy",
      "order": 54,
      "testament": "NT",
      "canonGroup": "protocanon",
      "numberOfChapters": 6,
      "totalNumberOfVerses": 113
    },
    {
      "id": "2TI",
      "name": "2 Timothy",
      "order": 55,
      "testament": "NT",
      "canonGroup": "protocanon",
      "numberOfChapters": 4,
      "totalNumberOfVerses": 83
    },
    {
      "id": "TIT",
      "name": "Titus",
      "order": 56,
      "testament": "NT",
      "canonGroup": "protocanon",
      "numberOfChapters": 3,
      "totalNumberOfVerses": 46
    },
    {
      "id": "PHM",
      "name": "Philemon",
      "order": 57,
      "testament": "NT",
      "canonGroup": "protocanon",
      "numberOfChapters": 1,
      "totalNumberOfVerses": 25
    },
    {
      "id": "HEB",
      "name": "Hebrews",
      "order": 58,
      "testament": "NT",
      "canonGroup": "protocanon",
      "numberOfChapters": 13,
      "totalNumberOfVerses": 303
    },
    {
      "id": "JAS",
      "name": "James",
      "order": 59,
      "testament": "NT",
      "canonGroup": "protocanon",
      "numberOfChapters": 5,
      "totalNumberOfVerses": 108
    },
    {
      "id": "1PE",
      "name": "1 Peter",
      "order": 60,
      "testament": "NT",
      "canonGroup": "protocanon",
      "numberOfChapters": 5,
      "totalNumberOfVerses": 105
    },
    {
      "id": "2PE",
      "name": "2 Peter",
      "order": 61,
      "testament": "NT",
      "canonGroup": "protocanon",
      "numberOfChapters": 3,
      "totalNumberOfVerses": 61
    },
    {
      "id": "1JN",
      "name": "1 John",
      "order": 62,
      "testament": "NT",
      "canonGroup": "protocanon",
      "numberOfChapters": 5,
      "totalNumberOfVerses": 105
    },
    {
      "id": "2JN",
      "name": "2 John",
      "order": 63,
      "testament": "NT",
      "canonGroup": "protocanon",
      "numberOfChapters": 1,
      "totalNumberOfVerses": 13
    },
    {
      "id": "3JN",
      "name": "3 John",
      "order": 64,
      "testament": "NT",
      "canonGroup": "protocanon",
      "numberOfChapters": 1,
      "totalNumberOfVerses": 14
    },
    {
      "id": "JUD",
      "name": "Jude",
      "order": 65,
      "testament": "NT",
      "canonGroup": "protocanon",
      "numberOfChapters": 1,
      "totalNumberOfVerses": 25
    },
    {
      "id": "REV",
      "name": "Revelation",
      "order": 66,
      "testament": "NT",
      "canonGroup": "protocanon",
      "numberOfChapters": 22,
      "totalNumberOfVerses": 404
    }
  ]
}